zengrad_pytorch/__init__.py
zengrad_pytorch/zengrad_pytorch.py
zengrad_pytorch-0.0.1.dist-info/METADATA
zengrad_pytorch-0.0.1.dist-info/WHEEL
zengrad_pytorch-0.0.1.dist-info/top_level.txt
zengrad_pytorch-0.0.1.dist-info/RECORD
