Metadata-Version: 2.1
Name: zengrad-pytorch
Version: 0.0.1
Summary: ZenGrad Optimizer - Pytorch
Home-page: https://github.com/XenReZ/ZenGrad-PyTorch
Author: Rishi Chaitanya
Author-email: rishichaitanya888@gmail.com
License: Apache-2.0
Classifier: Programming Language :: Python :: 3
Classifier: License :: OSI Approved :: Apache Software License
Classifier: Operating System :: OS Independent
Classifier: Intended Audience :: Developers
Classifier: Intended Audience :: Science/Research
Classifier: Topic :: Scientific/Engineering :: Artificial Intelligence
Requires-Python: >=3.6
Requires-Dist: torch>=1.6.0
